gym_cache/__init__.py
gym_cache/envs/__init__.py
gym_cache/envs/cache_continous.py
gym_cache/envs/cache_env.py
gym_cache/envs/cache_env_actor_cleanup.py
gym_cache/envs/cache_env_full.py
gym_cache-1.0.3.data/scripts/unit.py
gym_cache-1.0.3.dist-info/LICENSE
gym_cache-1.0.3.dist-info/METADATA
gym_cache-1.0.3.dist-info/WHEEL
gym_cache-1.0.3.dist-info/top_level.txt
gym_cache-1.0.3.dist-info/RECORD
