Metadata-Version: 2.1
Name: gym-cache
Version: 1.0.3
Summary: gym environment simulating file cache.
Home-page: https://github.com/ivukotic/gym-cache
Author: Ilija Vukotic
Author-email: ivukotic@cern.ch
License: UNKNOWN
Platform: UNKNOWN
Classifier: Programming Language :: Python :: 3
Classifier: License :: OSI Approved :: MIT License
Classifier: Operating System :: OS Independent
Requires-Dist: gym (>=0.2.3)
Requires-Dist: pandas (>=0.24.2)
Requires-Dist: scikit-learn (>=0.22.1)
